win32session.cp312-win_amd64.pyd
win32session-0.1.0.dist-info/licenses/LICENSE
win32session-0.1.0.dist-info/METADATA
win32session-0.1.0.dist-info/WHEEL
win32session-0.1.0.dist-info/top_level.txt
win32session-0.1.0.dist-info/RECORD
